xesrepair/__init__.py
xesrepair/add_cdn.py
xesrepair/common.py
xesrepair/complete_filter.py
xesrepair/complete_template.py
xesrepair/judge_error.py
xesrepair/package_manager.py
xesrepair/repair_dll.py
xesrepair/repair_numpy.py
xesrepair/update_cert.py
xesrepair-0.2.16.dist-info/METADATA
xesrepair-0.2.16.dist-info/WHEEL
xesrepair-0.2.16.dist-info/top_level.txt
xesrepair-0.2.16.dist-info/zip-safe
xesrepair-0.2.16.dist-info/RECORD
