Metadata-Version: 2.1
Name: xesrepair
Version: 0.2.16
Summary: 学而思编程助手专属工具库
Home-page: https://www.python.org/
Author: zhushaodong123
Author-email: UNKNOWN
License: NEU
Platform: UNKNOWN
Classifier: Programming Language :: Python
Classifier: Intended Audience :: Developers
Classifier: Operating System :: OS Independent
